easyroutine/__init__.py
easyroutine/console/__init__.py
easyroutine/console/progress.py
easyroutine/copilot/default.instructions.md
easyroutine/inference/__init__.py
easyroutine/inference/base_model_interface.py
easyroutine/inference/litellm_model_interface.py
easyroutine/inference/vllm_model_interface.py
easyroutine/interpretability/__init__.py
easyroutine/interpretability/ablation.py
easyroutine/interpretability/activation_cache.py
easyroutine/interpretability/activation_saver.py
easyroutine/interpretability/config/config.yaml
easyroutine/interpretability/hooked_model.py
easyroutine/interpretability/hooks.py
easyroutine/interpretability/interventions.py
easyroutine/interpretability/models.py
easyroutine/interpretability/module_wrappers/T5_attention.py
easyroutine/interpretability/module_wrappers/__init__.py
easyroutine/interpretability/module_wrappers/base.py
easyroutine/interpretability/module_wrappers/chameleon_attention.py
easyroutine/interpretability/module_wrappers/gemma3_attention.py
easyroutine/interpretability/module_wrappers/llama_attention.py
easyroutine/interpretability/module_wrappers/manager.py
easyroutine/interpretability/module_wrappers/mistral_attention.py
easyroutine/interpretability/module_wrappers/qwen2_attention.py
easyroutine/interpretability/token_index.py
easyroutine/interpretability/tools/__init__.py
easyroutine/interpretability/tools/logit_lens.py
easyroutine/interpretability/utils.py
easyroutine/logger.py
easyroutine/utils.py
easyroutine-1.1.5.dist-info/METADATA
easyroutine-1.1.5.dist-info/WHEEL
easyroutine-1.1.5.dist-info/licenses/LICENSE
easyroutine-1.1.5.dist-info/RECORD
