Metadata-Version: 2.4
Name: easyroutine
Version: 1.1.5
Summary: 
License-File: LICENSE
Author: Francesc0rtu
Author-email: francescortu@live.it
Requires-Python: >=3.10,<3.13
Classifier: Programming Language :: Python :: 3
Classifier: Programming Language :: Python :: 3.10
Classifier: Programming Language :: Python :: 3.11
Classifier: Programming Language :: Python :: 3.12
Requires-Dist: accelerate (>=1.1.1,<2.0.0)
Requires-Dist: einops (>=0.8.0,<0.9.0)
Requires-Dist: litellm (>=1.74.0,<2.0.0)
Requires-Dist: numpy (>=1.24,<2)
Requires-Dist: pandas (>=2.3.0,<3.0.0)
Requires-Dist: pydantic (>=2.10.6,<3.0.0)
Requires-Dist: pytest (>=8.3.3,<9.0.0)
Requires-Dist: python-dotenv (>=1.0.1,<2.0.0)
Requires-Dist: pyyaml (>=6.0.2,<7.0.0)
Requires-Dist: rich (>=13.9.4,<14.0.0)
Requires-Dist: sentencepiece (>=0.2.0,<0.3.0)
Requires-Dist: torch (>=2.4.0,<3.0.0)
Requires-Dist: torchvision (>=0.22,<0.23)
Requires-Dist: transformers (==4.51.1)
Requires-Dist: vllm (==0.9)
